{"data": [{"image": "//a.travel-assets.com/lxweb/media-vault/219608_l.jpeg?v=101827", "name": "Golden Gate Bridge to Sausalito Guided Bike Tour", "moods": [{"mood": "adventurous", "score": 0.2134650351989068}, {"mood": "romantic", "score": 0.121005615494474}, {"mood": "comical", "score": 0.039229834353353366}, {"mood": "relaxed", "score": 0.03521760380875464}], "latlng": [37.7749295, -122.4194155], "price": "$55", "type": "activity", "id": "219608", "keywords": [["Tours", 0.4887428044], ["Bike", 0.441898528], ["Bike Tour", 0.40868474460000004], ["Adventures", 0.33969668070000003], ["Sightseeing", 0.270949264]]}, {"image": "//a.travel-assets.com/lxweb/media-vault/219624_l.jpeg?v=101827", "name": "Golden Gate Bridge Guided Bike Tour", "moods": [{"mood": "adventurous", "score": 0.1518949303290571}, {"mood": "romantic", "score": 0.04172859306790638}, {"mood": "relaxed", "score": 0.033189417065444884}, {"mood": "comical", "score": 0.015420154306409665}], "latlng": [37.7749295, -122.4194155], "price": "$55", "type": "activity", "id": "219624", "keywords": [["Tours", 0.7815710872], ["Bike", 0.441898528], ["Bike Tour", 0.40868474460000004], ["Sightseeing", 0.3218878636], ["Gate", 0.227199264]]}, {"image": "//a.travel-assets.com/lxweb/media-vault/219750_l.jpeg?v=101827", "name": "Chinatown & North Beach Culinary Tour", "moods": [{"mood": "adventurous", "score": 0.10053089178496172}, {"mood": "romantic", "score": 0.04304640720558078}, {"mood": "relaxed", "score": 0.030369212693609843}], "latlng": [37.7941378, -122.4077914], "price": "$69", "type": "activity", "id": "219750", "keywords": [["Tours", 0.4756451613], ["Food", 0.33969668070000003], ["Drink", 0.2718878636], ["Sightseeing", 0.270949264], ["Walking", 0.26852579460000003]]}, {"image": "//a.travel-assets.com/lxweb/media-vault/219744_l.jpeg?v=101827", "name": "North Beach & Little Italy Culinary Tour", "moods": [{"mood": "adventurous", "score": 0.06657490853752157}, {"mood": "relaxed", "score": 0.030066785097909325}, {"mood": "comical", "score": 0.009672934290704833}, {"mood": "romantic", "score": 0.00792134392094958}], "latlng": [37.8007619, -122.4108045], "price": "$69", "type": "activity", "id": "219744", "keywords": [["Tours", 0.48231182800000005], ["Food", 0.33969668070000003], ["Bike", 0.277199264], ["Italy", 0.27532258060000003], ["Drink", 0.2718878636]]}, {"image": "//a.travel-assets.com/lxweb/media-vault/286257_l.jpeg?v=101827", "name": "Hippie Volkswagen Bus City Tour", "moods": [{"mood": "adventurous", "score": 0.16518676243008867}, {"mood": "romantic", "score": 0.09996650931190723}, {"mood": "relaxed", "score": 0.025342318538606613}, {"mood": "comical", "score": 0.014767955168763553}], "latlng": [37.7749295, -122.4194155], "price": "$48", "type": "activity", "id": "286257", "keywords": [["Tours", 0.4887428044], ["Hippie", 0.277199264], ["Sightseeing", 0.270949264], ["City", 0.2447222222], ["Attractions", 0.24174057370000002]]}, {"image": "//a.travel-assets.com/lxweb/media-vault/219776_l.jpeg?v=101827", "name": "California Sunset Cruise", "moods": [{"mood": "adventurous", "score": 0.19930412849529167}, {"mood": "romantic", "score": 0.08970527441218179}, {"mood": "relaxed", "score": 0.016807389141468537}, {"mood": "comical", "score": 0.012212173451633324}], "latlng": [37.8059887, -122.4099154], "price": "$64", "type": "activity", "id": "219776", "keywords": [["Cruises", 0.6176952482], ["Tours", 0.4756451613], ["Water", 0.2893714022], ["California", 0.227199264], ["Sightseeing", 0.220949264]]}, {"image": "//a.travel-assets.com/lxweb/media-vault/219716_l.jpeg?v=101827", "name": "Dinner & Dancing Cruise", "moods": [{"mood": "adventurous", "score": 0.18146888807592665}, {"mood": "romantic", "score": 0.10496776944447415}, {"mood": "relaxed", "score": 0.020124341264784372}, {"mood": "comical", "score": 0.012212173451633324}], "latlng": [37.7749295, -122.4194155], "price": "$136", "type": "activity", "id": "219716", "keywords": [["Cruises", 0.6893933614000001], ["Tours", 0.4756451613], ["Dancing", 0.2917114695], ["Water", 0.2893714022], ["Food", 0.26852579460000003]]}, {"image": "//a.travel-assets.com/lxweb/media-vault/367252_l.jpeg?v=101827", "name": "Classic San Francisco & Alcatraz Tour in Spanish", "moods": [{"mood": "adventurous", "score": 0.15133514004326293}, {"mood": "romantic", "score": 0.10502057565442964}, {"mood": "relaxed", "score": 0.019595707745902826}], "latlng": [37.7959362, -122.4000032], "price": "$110", "type": "activity", "id": "367252", "keywords": [["Tours", 0.6815710872], ["Sightseeing", 0.3218878636], ["Spanish", 0.2700564069], ["Classic", 0.24512433360000002], ["Attractions", 0.22820321400000002]]}, {"image": "//a.travel-assets.com/lxweb/media-vault/281275_l.jpeg?v=101827", "name": "The Original San Francisco Gourmet Chocolate Tour", "moods": [{"mood": "adventurous", "score": 0.06595356213441483}, {"mood": "relaxed", "score": 0.03392487119472648}, {"mood": "romantic", "score": 0.021741761550437583}, {"mood": "comical", "score": 0.009672934290704833}], "latlng": [37.7749295, -122.4194155], "price": "$55", "type": "activity", "id": "281275", "keywords": [["Tours", 0.4756451613], ["Food", 0.33969668070000003], ["Bike", 0.277199264], ["Drink", 0.2718878636], ["Chocolate", 0.227199264]]}, {"image": "//a.travel-assets.com/lxweb/media-vault/273049_l.jpeg?v=101827", "name": "NightLife at the California Academy of Sciences", "moods": [{"mood": "romantic", "score": 0.09496094662747966}, {"mood": "adventurous", "score": 0.06350213615255869}, {"mood": "relaxed", "score": 0.05359186368996073}, {"mood": "comical", "score": 0.0035404179594888566}], "latlng": [37.769731, -122.4661436], "price": "$15", "type": "activity", "id": "273049", "keywords": [["Nightlife", 0.49205158920000003], ["Attractions", 0.24174057370000002], ["California", 0.227199264], ["Academy", 0.227199264], ["Sciences", 0.1846922061]]}, {"image": "//a.travel-assets.com/lxweb/media-vault/304172_l.jpeg?v=101827", "name": "Muir Woods, Giant Redwoods & Sausalito", "moods": [{"mood": "adventurous", "score": 0.17023732368562725}, {"mood": "romantic", "score": 0.03603693007981309}, {"mood": "comical", "score": 0.012212173451633324}, {"mood": "relaxed", "score": 0.008553582530775946}], "latlng": [37.8953689, -122.5780709], "price": "$62", "type": "activity", "id": "304172", "keywords": [["Tours", 0.48231182800000005], ["Cruises", 0.33969668070000003], ["Water", 0.2893714022], ["Giant", 0.2878225806], ["Trips", 0.277199264]]}, {"image": "//a.travel-assets.com/lxweb/media-vault/376350_l.jpeg?v=101827", "name": "Combo Tour: Wine tasting & San Francisco Bay Cruise", "moods": [{"mood": "adventurous", "score": 0.16335323133352317}, {"mood": "romantic", "score": 0.07245689615239365}, {"mood": "relaxed", "score": 0.017923086632024625}], "latlng": [38.4274315, -122.3943299], "price": "$110", "type": "activity", "id": "376350", "keywords": [["Tours", 0.6815710872], ["Sightseeing", 0.3218878636], ["Combo", 0.270949264], ["Cruise", 0.227199264], ["Wine", 0.227199264]]}, {"image": "//a.travel-assets.com/lxweb/media-vault/408930_l.jpeg?v=101827", "name": "De Young Un-Highlights Tour", "moods": [{"mood": "adventurous", "score": 0.12883118117696352}, {"mood": "romantic", "score": 0.044486984323373786}, {"mood": "relaxed", "score": 0.0291870715963071}], "latlng": [37.7715158, -122.468647], "price": "$39", "type": "activity", "id": "408930", "keywords": [["Tours", 0.6815710872], ["Sightseeing", 0.270949264], ["Un", 0.227199264], ["Highlights", 0.227199264], ["Young", 0.21852579460000002]]}, {"image": "//a.travel-assets.com/lxweb/media-vault/277505_l.jpeg?v=101827", "name": "Mission District Food Tour", "moods": [{"mood": "adventurous", "score": 0.10053089178496172}, {"mood": "romantic", "score": 0.058751696804595396}, {"mood": "relaxed", "score": 0.03432546173743733}, {"mood": "comical", "score": 0.0008065039413936751}], "latlng": [37.7598648, -122.4147977], "price": "$84", "type": "activity", "id": "277505", "keywords": [["Food", 0.6176952482], ["Tours", 0.4756451613], ["Drink", 0.2718878636], ["Sightseeing", 0.270949264], ["District", 0.2628225806]]}, {"image": "//a.travel-assets.com/lxweb/media-vault/304158_l.jpeg?v=101827", "name": "City Highlights Tour", "moods": [{"mood": "adventurous", "score": 0.17593495906927656}, {"mood": "romantic", "score": 0.040832235506789064}, {"mood": "relaxed", "score": 0.022894293029980427}], "latlng": [37.7749295, -122.4194155], "price": "$62", "type": "activity", "id": "304158", "keywords": [["Tours", 0.6815710872], ["Sightseeing", 0.2960257946], ["Trips", 0.277199264], ["City", 0.2447222222], ["Highlights", 0.227199264]]}, {"image": "//a.travel-assets.com/lxweb/media-vault/277351_l.jpeg?v=101827", "name": "Streets of City by the Bay Guided Bike Tour", "moods": [{"mood": "adventurous", "score": 0.22037575113193142}, {"mood": "romantic", "score": 0.12603897238319273}, {"mood": "comical", "score": 0.039229834353353366}, {"mood": "relaxed", "score": 0.03680053078835746}], "latlng": [37.7749295, -122.4194155], "price": "$95", "type": "activity", "id": "277351", "keywords": [["Tours", 0.4887428044], ["Bike", 0.441898528], ["Bike Tour", 0.40868474460000004], ["Adventures", 0.33969668070000003], ["Sightseeing", 0.3097757946]]}, {"image": "//a.travel-assets.com/lxweb/media-vault/273069_l.jpeg?v=101827", "name": "Segway City Night Tour", "moods": [{"mood": "adventurous", "score": 0.11321208872142126}, {"mood": "romantic", "score": 0.08388908229863937}, {"mood": "relaxed", "score": 0.044313559461601676}, {"mood": "comical", "score": 0.002444191331816212}], "latlng": [37.7749295, -122.4194155], "price": "$75", "type": "activity", "id": "273069", "keywords": [["Tours", 0.4887428044], ["Nightlife", 0.33969668070000003], ["Sightseeing", 0.270949264], ["Walking", 0.26852579460000003], ["City", 0.2447222222]]}, {"image": "//a.travel-assets.com/lxweb/media-vault/273053_l.jpeg?v=101827", "name": "VIP NightLife Tour at the California Academy of Sciences", "moods": [{"mood": "romantic", "score": 0.12865422931509177}, {"mood": "adventurous", "score": 0.12701580644358465}, {"mood": "relaxed", "score": 0.04735641258347812}, {"mood": "comical", "score": 0.0034686530435722386}], "latlng": [37.769731, -122.4661436], "price": "$59", "type": "activity", "id": "273053", "keywords": [["Tours", 0.48231182800000005], ["Nightlife", 0.48207761400000004], ["Sightseeing", 0.270949264], ["VIP", 0.270949264], ["Attractions", 0.24174057370000002]]}, {"image": "//a.travel-assets.com/lxweb/media-vault/277243_l.jpeg?v=101827", "name": "Nob Hill Walking Tour with Optional Lunch", "moods": [{"mood": "adventurous", "score": 0.13446523326389806}, {"mood": "romantic", "score": 0.0632422694468815}, {"mood": "relaxed", "score": 0.041939383635580696}, {"mood": "comical", "score": 0.009672934290704833}], "latlng": [37.793014, -122.416113], "price": "$40", "type": "activity", "id": "277243", "keywords": [["Tours", 0.6815710872], ["Walking", 0.5120515892], ["Sightseeing", 0.3218878636], ["Bike", 0.277199264], ["Lunch", 0.2700564069]]}, {"image": "//a.travel-assets.com/lxweb/media-vault/277519_l.jpeg?v=101827", "name": "Craft Cocktail Tour", "moods": [{"mood": "adventurous", "score": 0.11171778253762076}, {"mood": "romantic", "score": 0.04304640720558078}, {"mood": "relaxed", "score": 0.03915439479447704}, {"mood": "comical", "score": 0.007928172390704832}], "latlng": [37.7749295, -122.4194155], "price": "$72", "type": "activity", "id": "277519", "keywords": [["Tours", 0.4756451613], ["Food", 0.33969668070000003], ["Drink", 0.2718878636], ["Sightseeing", 0.270949264], ["Bike", 0.227199264]]}, {"image": "//a.travel-assets.com/lxweb/media-vault/372894_l.jpeg?v=101827", "name": "Friday Night Bay Lights Sailing Adventure", "moods": [{"mood": "adventurous", "score": 0.129455923542983}, {"mood": "romantic", "score": 0.07337301703485954}, {"mood": "relaxed", "score": 0.025307893306570718}, {"mood": "comical", "score": 0.014206682308353612}], "latlng": [37.8590937, -122.4852507], "price": "$70", "type": "activity", "id": "372894", "keywords": [["Tours", 0.5756451613], ["Cruises", 0.33969668070000003], ["Water", 0.2893714022], ["Friday", 0.2878225806], ["Nightlife", 0.277199264]]}, {"image": "//a.travel-assets.com/lxweb/media-vault/219698_l.jpeg?v=101827", "name": "Historical LGBT Walking Tour", "moods": [{"mood": "adventurous", "score": 0.1298620557577605}, {"mood": "romantic", "score": 0.03837591073584993}, {"mood": "relaxed", "score": 0.025385373892482195}, {"mood": "comical", "score": 0.009672934290704833}], "latlng": [37.7609082, -122.4350043], "price": "$30", "type": "activity", "id": "219698", "keywords": [["Tours", 0.6815710872], ["Walking", 0.4245515892], ["Sightseeing", 0.2960257946], ["Bike", 0.277199264], ["LGBT", 0.220949264]]}, {"image": "//a.travel-assets.com/lxweb/media-vault/219704_l.jpeg?v=101827", "name": "Exploratorium Hands-On Science Museum Admission", "moods": [{"mood": "romantic", "score": 0.03170859999757346}, {"mood": "adventurous", "score": 0.02799910833375792}, {"mood": "comical", "score": 0.010868465985779233}, {"mood": "relaxed", "score": 0.006841269030934784}], "latlng": [37.8015558, -122.3975488], "price": "$30", "type": "activity", "id": "219704", "keywords": [["Exploratorium", 0.270949264], ["Attractions", 0.24174057370000002], ["Museum", 0.227199264], ["Admission", 0.227199264], ["Hands", 0.2132670523]]}, {"image": "//a.travel-assets.com/lxweb/media-vault/334752_l.jpeg?v=101827", "name": "City Highlights Segway Tour", "moods": [{"mood": "adventurous", "score": 0.134338471819854}, {"mood": "romantic", "score": 0.03837591073584993}, {"mood": "relaxed", "score": 0.03249911313294734}, {"mood": "comical", "score": 0.009672934290704833}], "latlng": [37.7749295, -122.4194155], "price": "$70", "type": "activity", "id": "334752", "keywords": [["Tours", 0.6815710872], ["Sightseeing", 0.2960257946], ["Bike", 0.277199264], ["Walking", 0.26852579460000003], ["City", 0.2447222222]]}, {"image": "//a.travel-assets.com/lxweb/media-vault/281739_l.jpeg?v=101827", "name": "Haight-Ashbury Walking Tour: A Musical Trip of the '60s", "moods": [{"mood": "adventurous", "score": 0.13446523326389806}, {"mood": "romantic", "score": 0.07634298852533553}, {"mood": "comical", "score": 0.0391668235177729}, {"mood": "relaxed", "score": 0.03792701163187482}], "latlng": [37.7692204, -122.4481393], "price": "$18", "type": "activity", "id": "281739", "keywords": [["Tours", 0.6815710872], ["Walking", 0.47035347600000005], ["Sightseeing", 0.3218878636], ["Musical", 0.2917114695], ["Bike", 0.277199264]]}, {"image": "//a.travel-assets.com/lxweb/media-vault/281281_l.jpeg?v=101827", "name": "Ultimate Gourmet Chocolate Tour with Wine, Beer & Cocktail Pairings", "moods": [{"mood": "adventurous", "score": 0.10053089178496172}, {"mood": "romantic", "score": 0.04304640720558078}, {"mood": "relaxed", "score": 0.030369212693609843}], "latlng": [37.7945742, -122.3999445], "price": "$85", "type": "activity", "id": "281281", "keywords": [["Tours", 0.4756451613], ["Food", 0.33969668070000003], ["Drink", 0.2718878636], ["Sightseeing", 0.270949264], ["Walking", 0.24602579460000001]]}, {"image": "//a.travel-assets.com/lxweb/media-vault/284663_l.jpeg?v=101827", "name": "After Dark: Adults-Only Evening Exhibits at the Exploratorium", "moods": [{"mood": "romantic", "score": 0.07357324720659475}, {"mood": "relaxed", "score": 0.0670362371228758}, {"mood": "adventurous", "score": 0.03735636915009598}, {"mood": "comical", "score": 0.022357260083123328}], "latlng": [37.8015558, -122.3975488], "price": "$15", "type": "activity", "id": "284663", "keywords": [["Dark", 0.277199264], ["Adults", 0.277199264], ["Attractions", 0.24174057370000002], ["Evening", 0.227199264], ["Exploratorium", 0.220949264]]}, {"image": "//a.travel-assets.com/lxweb/media-vault/285667_l.jpeg?v=101827", "name": "Private Sailing Cruise on the Bay", "moods": [{"mood": "adventurous", "score": 0.21583252685499935}, {"mood": "romantic", "score": 0.08023866420483292}, {"mood": "comical", "score": 0.012212173451633324}, {"mood": "relaxed", "score": 0.007824874944900828}], "latlng": [37.6909682, -122.3107517], "price": "$300", "type": "activity", "id": "285667", "keywords": [["Cruises", 0.6176952482], ["Private", 0.4831153012], ["Tours", 0.48231182800000005], ["Water", 0.2893714022], ["Bay", 0.2613829375]]}, {"image": "//a.travel-assets.com/lxweb/media-vault/249506_l.jpeg?v=101827", "name": "City Insider's Tour", "moods": [{"mood": "adventurous", "score": 0.16610381517274728}, {"mood": "romantic", "score": 0.040832235506789064}, {"mood": "relaxed", "score": 0.021780566032080135}], "latlng": [37.7749295, -122.4194155], "price": "$79", "type": "activity", "id": "249506", "keywords": [["Tours", 0.6815710872], ["Sightseeing", 0.2960257946], ["Trips", 0.277199264], ["City", 0.2447222222], ["Insider's", 0.227199264]]}, {"image": "//a.travel-assets.com/lxweb/media-vault/277327_l.jpeg?v=101827", "name": "Downtown Masters of the Craft Cocktail Tasting Tour", "moods": [{"mood": "adventurous", "score": 0.12349989028762076}, {"mood": "romantic", "score": 0.04304640720558078}, {"mood": "relaxed", "score": 0.04146895099447704}, {"mood": "comical", "score": 0.009672934290704833}], "latlng": [37.7749295, -122.4194155], "price": "$130", "type": "activity", "id": "277327", "keywords": [["Tours", 0.5756451613], ["Food", 0.33969668070000003], ["Bike", 0.277199264], ["Drink", 0.2718878636], ["Sightseeing", 0.270949264]]}, {"image": "//a.travel-assets.com/lxweb/media-vault/219804_l.jpeg?v=101827", "name": "Golden Gate Park Segway Tour", "moods": [{"mood": "adventurous", "score": 0.14378542926389806}, {"mood": "romantic", "score": 0.04172859306790638}, {"mood": "relaxed", "score": 0.026820941214577683}, {"mood": "comical", "score": 0.009672934290704833}], "latlng": [37.7694208, -122.4862138], "price": "$75", "type": "activity", "id": "219804", "keywords": [["Tours", 0.7815710872], ["Sightseeing", 0.3218878636], ["Bike", 0.277199264], ["Walking", 0.26852579460000003], ["Gate", 0.227199264]]}, {"image": "//a.travel-assets.com/lxweb/media-vault/381162_l.jpeg?v=101827", "name": "Combo Tour: Grand City Loop & Bay Cruise", "moods": [{"mood": "adventurous", "score": 0.16322646988947914}, {"mood": "romantic", "score": 0.0608356203660084}, {"mood": "relaxed", "score": 0.023982449750394277}], "latlng": [37.7749295, -122.4194155], "price": "$60", "type": "activity", "id": "381162", "keywords": [["Tours", 0.6815710872], ["Sightseeing", 0.2960257946], ["Combo", 0.270949264], ["City", 0.2447222222], ["Cruise", 0.227199264]]}, {"image": "//a.travel-assets.com/lxweb/media-vault/275383_l.jpeg?v=101827", "name": "Self-Guided City Tour in Classic Volkswagen Bug", "moods": [{"mood": "adventurous", "score": 0.11086443569091206}, {"mood": "romantic", "score": 0.05945119239732867}, {"mood": "relaxed", "score": 0.020023171244832598}], "latlng": [37.7749295, -122.4194155], "price": "$200", "type": "activity", "id": "275383", "keywords": [["Tours", 0.4887428044], ["Sightseeing", 0.270949264], ["City", 0.2447222222], ["Attractions", 0.24174057370000002], ["Guided", 0.22820321400000002]]}, {"image": "//a.travel-assets.com/lxweb/media-vault/372904_l.jpeg?v=101827", "name": "Sunday Morning Sailing Cruise Aboard the Freda B", "moods": [{"mood": "adventurous", "score": 0.22103077622315034}, {"mood": "romantic", "score": 0.13597953863816736}, {"mood": "relaxed", "score": 0.03869270345176531}, {"mood": "comical", "score": 0.014206682308353612}], "latlng": [37.8590937, -122.4852507], "price": "$81", "type": "activity", "id": "372904", "keywords": [["Cruises", 0.6176952482], ["Tours", 0.48231182800000005], ["Water", 0.2893714022], ["Nightlife", 0.277199264], ["Sightseeing", 0.270949264]]}, {"image": "//a.travel-assets.com/lxweb/media-vault/371862_l.jpeg?v=101827", "name": "Half-Day Sonoma Valley Wine Tour", "moods": [{"mood": "adventurous", "score": 0.10053089178496172}, {"mood": "romantic", "score": 0.04655429318276968}, {"mood": "relaxed", "score": 0.03997499604978268}, {"mood": "comical", "score": 0.010037892954776641}], "latlng": [38.291859, -122.4580356], "price": "$109", "type": "activity", "id": "371862", "keywords": [["Tours", 0.4756451613], ["Food", 0.33969668070000003], ["Drink", 0.2718878636], ["Sightseeing", 0.270949264], ["Valley", 0.227199264]]}, {"image": "//a.travel-assets.com/lxweb/media-vault/277357_l.jpeg?v=101827", "name": "Golden Gate Bridge Sunset Bike Tour with Guide", "moods": [{"mood": "adventurous", "score": 0.18687451232345018}, {"mood": "romantic", "score": 0.12491050364459774}, {"mood": "relaxed", "score": 0.05088062633826759}, {"mood": "comical", "score": 0.047728983656621767}], "latlng": [37.7749295, -122.4194155], "price": "$55", "type": "activity", "id": "277357", "keywords": [["Bike", 0.6293985280000001], ["Tours", 0.493372434], ["Adventures", 0.33969668070000003], ["Bike Tour", 0.3153514113], ["Nightlife", 0.2718878636]]}, {"image": "//a.travel-assets.com/lxweb/media-vault/277513_l.jpeg?v=101827", "name": "North Beach Food Tour", "moods": [{"mood": "adventurous", "score": 0.10985108778496172}, {"mood": "romantic", "score": 0.04894083001418444}, {"mood": "relaxed", "score": 0.03470665293743733}], "latlng": [37.8060532, -122.4103311], "price": "$84", "type": "activity", "id": "277513", "keywords": [["Food", 0.6176952482], ["Tours", 0.5756451613], ["Drink", 0.2718878636], ["Sightseeing", 0.270949264], ["Walking", 0.26852579460000003]]}, {"image": "//a.travel-assets.com/lxweb/media-vault/334746_l.jpeg?v=101827", "name": "Sunset Segway Tour", "moods": [{"mood": "adventurous", "score": 0.05551795205033519}, {"mood": "relaxed", "score": 0.04286094435247037}, {"mood": "romantic", "score": 0.01705730085674112}, {"mood": "comical", "score": 0.015523657522375025}], "latlng": [37.7749295, -122.4194155], "price": "$60", "type": "activity", "id": "334746", "keywords": [["Tours", 0.4756451613], ["Walking", 0.33969668070000003], ["Bike", 0.227199264], ["Segway", 0.220949264], ["Sunset", 0.220949264]]}, {"image": "//a.travel-assets.com/lxweb/media-vault/275369_l.jpeg?v=101827", "name": "North Beach Underground Walking Tour and Beat Museum", "moods": [{"mood": "adventurous", "score": 0.11212598420865141}, {"mood": "romantic", "score": 0.05784450092284001}, {"mood": "relaxed", "score": 0.04467350501145997}, {"mood": "comical", "score": 0.009672934290704833}], "latlng": [37.7749295, -122.4194155], "price": "$25", "type": "activity", "id": "275369", "keywords": [["Walking", 0.6120515892], ["Tours", 0.4887428044], ["Bike", 0.277199264], ["Beat", 0.27532258060000003], ["Sightseeing", 0.270949264]]}, {"image": "//a.travel-assets.com/lxweb/media-vault/372898_l.jpeg?v=101827", "name": "Sunday Sunset Sail Aboard the Freda B", "moods": [{"mood": "adventurous", "score": 0.16898320609929565}, {"mood": "romantic", "score": 0.10849808031949075}, {"mood": "relaxed", "score": 0.03599850229672589}, {"mood": "comical", "score": 0.014206682308353612}], "latlng": [37.8590937, -122.4852507], "price": "$70", "type": "activity", "id": "372898", "keywords": [["Tours", 0.48231182800000005], ["Cruises", 0.33969668070000003], ["Water", 0.2893714022], ["Nightlife", 0.277199264], ["Sightseeing", 0.270949264]]}, {"image": "//a.travel-assets.com/lxweb/media-vault/287225_l.jpeg?v=101827", "name": "7x7 Citywide Sightseeing Ride", "moods": [{"mood": "adventurous", "score": 0.19461069397920883}, {"mood": "romantic", "score": 0.08453753331802032}, {"mood": "relaxed", "score": 0.04837010904763619}, {"mood": "comical", "score": 0.024753619685653226}], "latlng": [37.7749295, -122.4194155], "price": "$99", "type": "activity", "id": "287225", "keywords": [["Tours", 0.6815710872], ["Sightseeing", 0.530353476], ["Bike", 0.277199264], ["Ride", 0.2700564069], ["Walking", 0.26852579460000003]]}, {"image": "//a.travel-assets.com/lxweb/media-vault/289553_l.jpeg?v=101827", "name": "Muir Woods Tour of California Coastal Redwoods", "moods": [{"mood": "adventurous", "score": 0.20818511484547836}, {"mood": "romantic", "score": 0.0363141843602813}, {"mood": "relaxed", "score": 0.017912392556327653}, {"mood": "comical", "score": 0.012212173451633324}], "latlng": [37.8953689, -122.5780709], "price": "$63", "type": "activity", "id": "289553", "keywords": [["Tours", 0.493372434], ["Cruises", 0.33969668070000003], ["Water", 0.2893714022], ["Trips", 0.277199264], ["Excursions", 0.270949264]]}, {"image": "//a.travel-assets.com/lxweb/media-vault/289545_l.jpeg?v=101827", "name": "Grand City Sightseeing Excursion", "moods": [{"mood": "adventurous", "score": 0.22490671750396682}, {"mood": "romantic", "score": 0.059995438053427406}, {"mood": "relaxed", "score": 0.04943325062164316}], "latlng": [37.7749295, -122.4194155], "price": "$59", "type": "activity", "id": "289545", "keywords": [["Excursions", 0.516898528], ["Sightseeing", 0.441898528], ["Day Trips", 0.2891945439], ["Trips", 0.24602579460000001], ["City", 0.2447222222]]}, {"image": "//a.travel-assets.com/lxweb/media-vault/277561_l.jpeg?v=101827", "name": "Beginner Rock Climbing Lesson", "moods": [{"mood": "adventurous", "score": 0.19653180773805898}, {"mood": "romantic", "score": 0.08861413126125015}, {"mood": "comical", "score": 0.023809680046943702}, {"mood": "relaxed", "score": 0.01796070556238035}], "latlng": [37.2306929, -122.0955322], "price": "$99", "type": "activity", "id": "277561", "keywords": [["Adventures", 0.33969668070000003], ["Trips", 0.277199264], ["Excursions", 0.270949264], ["Lesson", 0.2700564069], ["Day Trips", 0.2588275715]]}, {"image": "//a.travel-assets.com/lxweb/media-vault/281285_l.jpeg?v=101827", "name": "Gourmet Food Tour of Downtown Napa", "moods": [{"mood": "adventurous", "score": 0.1148010406907275}, {"mood": "romantic", "score": 0.04894083001418444}, {"mood": "relaxed", "score": 0.04506942158509826}, {"mood": "comical", "score": 0.009672934290704833}], "latlng": [38.2975381, -122.286865], "price": "$85", "type": "activity", "id": "281285", "keywords": [["Food", 0.6176952482], ["Tours", 0.48231182800000005], ["Bike", 0.277199264], ["Drink", 0.2718878636], ["Sightseeing", 0.270949264]]}, {"image": "//a.travel-assets.com/lxweb/media-vault/285663_l.jpeg?v=101827", "name": "Private Sunset Golden Gate Cruise", "moods": [{"mood": "adventurous", "score": 0.232605659571815}, {"mood": "romantic", "score": 0.08297179403477523}, {"mood": "comical", "score": 0.012212173451633324}, {"mood": "relaxed", "score": 0.008598612254899916}], "latlng": [37.6909682, -122.3107517], "price": "$300", "type": "activity", "id": "285663", "keywords": [["Cruises", 0.6608219328], ["Tours", 0.5756451613], ["Private", 0.4831153012], ["Water", 0.2893714022], ["Gate", 0.227199264]]}, {"image": "//a.travel-assets.com/lxweb/media-vault/277551_l.jpeg?v=101827", "name": "Beginner Surfing Lessons", "moods": [{"mood": "adventurous", "score": 0.06424367257771146}, {"mood": "relaxed", "score": 0.040289415970490836}, {"mood": "comical", "score": 0.0386918987825584}, {"mood": "romantic", "score": 0.017223098334201218}], "latlng": [36.9741171, -122.0307963], "price": "$99", "type": "activity", "id": "277551", "keywords": [["Water", 0.3857855436], ["Lessons", 0.227199264], ["Surfing", 0.220949264], ["Beginner", 0.220949264], ["Activities", 0.1318924676]]}, {"image": "//a.travel-assets.com/lxweb/media-vault/275391_l.jpeg?v=101827", "name": "Tales of the City Hiking Tour", "moods": [{"mood": "adventurous", "score": 0.21375955346963}, {"mood": "romantic", "score": 0.09916806587577198}, {"mood": "relaxed", "score": 0.03742674041309927}, {"mood": "comical", "score": 0.025597557903728835}], "latlng": [37.7749295, -122.4194155], "price": "$49", "type": "activity", "id": "275391", "keywords": [["Tours", 0.7815710872], ["Sightseeing", 0.3218878636], ["Bike", 0.277199264], ["City", 0.2447222222], ["Adventures", 0.227199264]]}, {"image": "//a.travel-assets.com/lxweb/media-vault/304232_l.jpeg?v=101827", "name": "City Highlights Tour with Bay Cruise", "moods": [{"mood": "adventurous", "score": 0.24958472408925544}, {"mood": "romantic", "score": 0.058173449512045124}, {"mood": "relaxed", "score": 0.02005541046815989}, {"mood": "comical", "score": 0.012212173451633324}], "latlng": [37.6909682, -122.3107517], "price": "$91", "type": "activity", "id": "304232", "keywords": [["Cruises", 0.5608219328], ["Tours", 0.493372434], ["Water", 0.2893714022], ["Trips", 0.277199264], ["Excursions", 0.270949264]]}, {"image": "//a.travel-assets.com/lxweb/media-vault/284655_l.jpeg?v=101827", "name": "Classic Combo Walking Tour: Chinatown & North Beach", "moods": [{"mood": "adventurous", "score": 0.14968574304356955}, {"mood": "relaxed", "score": 0.016378229225467524}, {"mood": "romantic", "score": 0.0027262435705589674}], "latlng": [37.7941378, -122.4077914], "price": "$36", "type": "activity", "id": "284655", "keywords": [["Walking", 0.5370515892000001], ["Tours", 0.4756451613], ["Excursions", 0.3097757946], ["Day Trips", 0.2891945439], ["Trips", 0.2718878636]]}, {"image": "//a.travel-assets.com/lxweb/media-vault/249238_l.jpeg?v=101827", "name": "Supper Club Bay Cruise with Dinner & Dancing", "moods": [{"mood": "adventurous", "score": 0.14404962251911396}, {"mood": "romantic", "score": 0.1327116888426731}, {"mood": "relaxed", "score": 0.04653940708248952}, {"mood": "comical", "score": 0.014206682308353612}], "latlng": [37.6909682, -122.3107517], "price": "$115", "type": "activity", "id": "249238", "keywords": [["Cruises", 0.6176952482], ["Dancing", 0.2917114695], ["Water", 0.2893714022], ["Nightlife", 0.277199264], ["Drink", 0.277199264]]}, {"image": "//a.travel-assets.com/lxweb/media-vault/281289_l.jpeg?v=101827", "name": "Gourmet Food Tour of Hayes Valley", "moods": [{"mood": "adventurous", "score": 0.06595356213441483}, {"mood": "relaxed", "score": 0.04360340475111592}, {"mood": "comical", "score": 0.019710827245481476}, {"mood": "romantic", "score": 0.017323652706742132}], "latlng": [37.7759073, -122.4245247], "price": "$85", "type": "activity", "id": "281289", "keywords": [["Food", 0.6176952482], ["Tours", 0.4756451613], ["Bike", 0.277199264], ["Drink", 0.2718878636], ["Valley", 0.227199264]]}, {"image": "//a.travel-assets.com/lxweb/media-vault/192714_l.jpeg?v=101827", "name": "Panoramic Night Tour", "moods": [{"mood": "adventurous", "score": 0.11585259365285004}, {"mood": "romantic", "score": 0.038603243298558756}, {"mood": "relaxed", "score": 0.018852396735018633}, {"mood": "comical", "score": 0.0004140837414946795}], "latlng": [37.7749295, -122.4194155], "price": "$30", "type": "activity", "id": "192714", "keywords": [["Tours", 0.6815710872], ["Sightseeing", 0.270949264], ["Panoramic", 0.220949264], ["Night", 0.21852579460000002]]}, {"image": "//a.travel-assets.com/lxweb/media-vault/284659_l.jpeg?v=101827", "name": "Radical Combo Walking Tour: the Castro & the Mission", "moods": [{"mood": "adventurous", "score": 0.17078763535333316}, {"mood": "romantic", "score": 0.04510241333587161}, {"mood": "relaxed", "score": 0.015721202913710482}, {"mood": "comical", "score": 0.0025984430488999854}], "latlng": [37.7692204, -122.4481393], "price": "$36", "type": "activity", "id": "284659", "keywords": [["Tours", 0.6815710872], ["Walking", 0.430353476], ["Sightseeing", 0.3218878636], ["Trips", 0.277199264], ["Mission", 0.2700564069]]}, {"image": "//a.travel-assets.com/lxweb/media-vault/307436_l.jpeg?v=101827", "name": "Golden Gate Bridge to Baker Beach Walking Tour", "moods": [{"mood": "adventurous", "score": 0.14378542926389806}, {"mood": "romantic", "score": 0.04172859306790638}, {"mood": "relaxed", "score": 0.026820941214577683}, {"mood": "comical", "score": 0.009672934290704833}], "latlng": [37.7988737, -122.4661937], "price": "$49", "type": "activity", "id": "307436", "keywords": [["Tours", 0.7815710872], ["Walking", 0.4245515892], ["Sightseeing", 0.3218878636], ["Baker", 0.2878225806], ["Bike", 0.277199264]]}, {"image": "//a.travel-assets.com/lxweb/media-vault/275365_l.jpeg?v=101827", "name": "Handcrafted in Dogpatch Tour with Wine, Beer & Food Tastings", "moods": [{"mood": "adventurous", "score": 0.11540042029592124}, {"mood": "romantic", "score": 0.04894083001418444}, {"mood": "relaxed", "score": 0.04509393590120914}, {"mood": "comical", "score": 0.009672934290704833}], "latlng": [37.7591221, -122.3895378], "price": "$79", "type": "activity", "id": "275365", "keywords": [["Food", 0.6176952482], ["Tours", 0.4887428044], ["Bike", 0.277199264], ["Drink", 0.2718878636], ["Sightseeing", 0.270949264]]}, {"image": "//a.travel-assets.com/lxweb/media-vault/277171_l.jpeg?v=101827", "name": "Beers & Bikes Tour with Alcatraz Admission", "moods": [{"mood": "adventurous", "score": 0.07483430941580593}, {"mood": "relaxed", "score": 0.03230652081229078}, {"mood": "comical", "score": 0.028166209019454803}, {"mood": "romantic", "score": 0.000732772373594304}], "latlng": [37.7749295, -122.4194155], "price": "$110", "type": "activity", "id": "277171", "keywords": [["Tours", 0.4756451613], ["Bike", 0.454398528], ["Bike Tours", 0.3153514113], ["Water", 0.291686217], ["Drink", 0.277199264]]}, {"image": "//a.travel-assets.com/lxweb/media-vault/275395_l.jpeg?v=101827", "name": "Presidio Exploration Hiking Tour", "moods": [{"mood": "adventurous", "score": 0.20928313740753646}, {"mood": "romantic", "score": 0.09916806587577198}, {"mood": "relaxed", "score": 0.030313001172634132}, {"mood": "comical", "score": 0.025597557903728835}], "latlng": [37.7988737, -122.4661937], "price": "$49", "type": "activity", "id": "275395", "keywords": [["Tours", 0.7815710872], ["Sightseeing", 0.3218878636], ["Bike", 0.277199264], ["Walking", 0.26852579460000003], ["Adventures", 0.227199264]]}, {"image": "//a.travel-assets.com/lxweb/media-vault/275357_l.jpeg?v=101827", "name": "Flight & Sunset Dinner Cruise", "moods": [{"mood": "adventurous", "score": 0.0629428489130591}, {"mood": "comical", "score": 0.028393532179055957}, {"mood": "relaxed", "score": 0.022363147443522594}, {"mood": "romantic", "score": 0.011753679413823877}], "latlng": [37.7749295, -122.4194155], "price": "$375", "type": "activity", "id": "275357", "keywords": [["Helicopter", 0.277199264], ["Air", 0.26765873020000003], ["Balloon", 0.24602579460000001], ["Flight", 0.2378225806], ["Tours", 0.2378225806]]}, {"image": "//a.travel-assets.com/lxweb/media-vault/307440_l.jpeg?v=101827", "name": "Sausalito to Golden Gate Bridge Overlook Walking Tour", "moods": [{"mood": "adventurous", "score": 0.14378542926389806}, {"mood": "romantic", "score": 0.04172859306790638}, {"mood": "relaxed", "score": 0.026820941214577683}, {"mood": "comical", "score": 0.009672934290704833}], "latlng": [37.8590937, -122.4852507], "price": "$49", "type": "activity", "id": "307440", "keywords": [["Tours", 0.7815710872], ["Walking", 0.4245515892], ["Sightseeing", 0.3218878636], ["Bike", 0.277199264], ["Sausalito", 0.270949264]]}, {"image": "//a.travel-assets.com/lxweb/media-vault/286269_l.jpeg?v=101827", "name": "City Lights by Night Volkswagen Bus Tour", "moods": [{"mood": "adventurous", "score": 0.12089354285401847}, {"mood": "romantic", "score": 0.07415501471938615}, {"mood": "relaxed", "score": 0.04265300373411756}, {"mood": "comical", "score": 0.0019562921782684014}], "latlng": [37.7749295, -122.4194155], "price": "$55", "type": "activity", "id": "286269", "keywords": [["Tours", 0.5756451613], ["Nightlife", 0.2718878636], ["Sightseeing", 0.270949264], ["City", 0.2447222222], ["Bus", 0.227199264]]}, {"image": "//a.travel-assets.com/lxweb/media-vault/277569_l.jpeg?v=101827", "name": "Wilderness Survival Skills Clinic", "moods": [{"mood": "adventurous", "score": 0.19653180773805898}, {"mood": "romantic", "score": 0.08925311510489578}, {"mood": "comical", "score": 0.038795382253553945}, {"mood": "relaxed", "score": 0.01796070556238035}], "latlng": [37.1304376, -122.1023133], "price": "$125", "type": "activity", "id": "277569", "keywords": [["Adventures", 0.33969668070000003], ["Trips", 0.277199264], ["Excursions", 0.270949264], ["Day Trips", 0.2588275715], ["Survival", 0.227199264]]}, {"image": "//a.travel-assets.com/lxweb/media-vault/277565_l.jpeg?v=101827", "name": "Beginner Mountain Biking Lesson", "moods": [{"mood": "adventurous", "score": 0.19653180773805898}, {"mood": "romantic", "score": 0.08861413126125015}, {"mood": "comical", "score": 0.023809680046943702}, {"mood": "relaxed", "score": 0.01796070556238035}], "latlng": [36.9988811, -122.0049409], "price": "$90", "type": "activity", "id": "277565", "keywords": [["Adventures", 0.33969668070000003], ["Trips", 0.277199264], ["Excursions", 0.270949264], ["Lesson", 0.2700564069], ["Day Trips", 0.2588275715]]}, {"image": "//a.travel-assets.com/lxweb/media-vault/296569_l.jpeg?v=101827", "name": "Muir Woods & Sausalito Half-Day Tour", "moods": [{"mood": "adventurous", "score": 0.1269852964875295}, {"mood": "romantic", "score": 0.045012956469632645}, {"mood": "relaxed", "score": 0.038211318973134414}], "latlng": [37.8953689, -122.5780709], "price": "$109", "type": "activity", "id": "296569", "keywords": [["Tours", 0.6815710872], ["Sightseeing", 0.2960257946], ["Woods", 0.277199264], ["Muir", 0.270949264], ["Sausalito", 0.220949264]]}, {"image": "//a.travel-assets.com/lxweb/media-vault/368906_l.jpeg?v=101827", "name": "Private Napa Valley Winetasting Tour", "moods": [{"mood": "adventurous", "score": 0.09610564624156265}, {"mood": "relaxed", "score": 0.028928608606421234}, {"mood": "romantic", "score": 0.02542304727227594}, {"mood": "comical", "score": 0.010037892954776641}], "latlng": [38.2975381, -122.286865], "price": "$420", "type": "activity", "id": "368906", "keywords": [["Tours", 0.4756451613], ["Private", 0.38311530120000004], ["Food", 0.33969668070000003], ["Drink", 0.2718878636], ["Valley", 0.227199264]]}, {"image": "//a.travel-assets.com/lxweb/media-vault/368914_l.jpeg?v=101827", "name": "Private Custom City Tour", "moods": [{"mood": "adventurous", "score": 0.13611773294200583}, {"mood": "romantic", "score": 0.04722192957389594}, {"mood": "relaxed", "score": 0.028733894926868425}, {"mood": "comical", "score": 0.0016170186368842099}], "latlng": [37.7749295, -122.4194155], "price": "$220", "type": "activity", "id": "368914", "keywords": [["Tours", 0.4887428044], ["Private", 0.3311815817], ["Sightseeing", 0.270949264], ["City", 0.2447222222], ["Custom", 0.178203214]]}, {"image": "//a.travel-assets.com/lxweb/media-vault/275399_l.jpeg?v=101827", "name": "City Heights & Jungles Hiking Tour", "moods": [{"mood": "adventurous", "score": 0.15081034719505454}, {"mood": "romantic", "score": 0.04551640376069397}, {"mood": "relaxed", "score": 0.04172505808252651}, {"mood": "comical", "score": 0.023227702134351266}], "latlng": [37.7749295, -122.4194155], "price": "$49", "type": "activity", "id": "275399", "keywords": [["Tours", 0.7815710872], ["Sightseeing", 0.3218878636], ["Bike", 0.277199264], ["City", 0.2447222222], ["Heights", 0.227199264]]}, {"image": "//a.travel-assets.com/lxweb/media-vault/264437_l.jpeg?v=101827", "name": "Champagne Brunch Cruise", "moods": [{"mood": "adventurous", "score": 0.18006407725159765}, {"mood": "romantic", "score": 0.07444392640252585}, {"mood": "relaxed", "score": 0.022907796470713532}, {"mood": "comical", "score": 0.012212173451633324}], "latlng": [37.7749295, -122.4194155], "price": "$100", "type": "activity", "id": "264437", "keywords": [["Cruises", 0.6893933614000001], ["Tours", 0.4756451613], ["Water", 0.2893714022], ["Food", 0.26852579460000003], ["Drink", 0.227199264]]}, {"image": "//a.travel-assets.com/lxweb/media-vault/334730_l.jpeg?v=101827", "name": "African Savanna Excursion", "moods": [{"mood": "adventurous", "score": 0.1532063238072699}, {"mood": "romantic", "score": 0.10907052018114198}, {"mood": "comical", "score": 0.023809680046943702}, {"mood": "relaxed", "score": 0.01560979371238035}], "latlng": [38.556943, -122.695526], "price": "$94", "type": "activity", "id": "334730", "keywords": [["Adventures", 0.33969668070000003], ["Attractions", 0.22820321400000002], ["African", 0.227199264], ["Excursion", 0.220949264], ["Savanna", 0.220949264]]}, {"image": "//a.travel-assets.com/lxweb/media-vault/275361_l.jpeg?v=101827", "name": "Gold & Guns Walking Tour with Cocktail Tastings", "moods": [{"mood": "adventurous", "score": 0.06657490853752157}, {"mood": "relaxed", "score": 0.030066785097909325}, {"mood": "comical", "score": 0.009672934290704833}, {"mood": "romantic", "score": 0.00792134392094958}], "latlng": [37.7749295, -122.4194155], "price": "$69", "type": "activity", "id": "275361", "keywords": [["Walking", 0.5370515892000001], ["Tours", 0.48231182800000005], ["Food", 0.33969668070000003], ["Bike", 0.277199264], ["Drink", 0.2718878636]]}, {"image": "//a.travel-assets.com/lxweb/media-vault/249528_l.jpeg?v=101827", "name": "Fisherman's Wharf Walking Tour", "moods": [{"mood": "adventurous", "score": 0.11174989335957684}, {"mood": "romantic", "score": 0.035125063284631206}, {"mood": "relaxed", "score": 0.013644476449512168}, {"mood": "comical", "score": 0.0015875596582394338}], "latlng": [37.8065278, -122.4207822], "price": "$57", "type": "activity", "id": "249528", "keywords": [["Tours", 0.6815710872], ["Sightseeing", 0.270949264], ["Fisherman's", 0.270949264], ["Wharf", 0.220949264], ["Walking", 0.21852579460000002]]}, {"image": "//a.travel-assets.com/lxweb/media-vault/277227_l.jpeg?v=101827", "name": "Chinatown Walking Tour", "moods": [{"mood": "adventurous", "score": 0.10053089178496172}, {"mood": "romantic", "score": 0.04304640720558078}, {"mood": "relaxed", "score": 0.030369212693609843}], "latlng": [37.7941378, -122.4077914], "price": "$35", "type": "activity", "id": "277227", "keywords": [["Walking", 0.5120515892], ["Tours", 0.4756451613], ["Food", 0.33969668070000003], ["Drink", 0.2718878636], ["Sightseeing", 0.270949264]]}, {"image": "//a.travel-assets.com/lxweb/media-vault/286273_l.jpeg?v=101827", "name": "Private Volkswagen Bus City Tour", "moods": [{"mood": "adventurous", "score": 0.1290496950705772}, {"mood": "romantic", "score": 0.04232498635156612}, {"mood": "relaxed", "score": 0.013677969311405823}], "latlng": [37.7749295, -122.4194155], "price": "$396", "type": "activity", "id": "286273", "keywords": [["Tours", 0.4756451613], ["Private", 0.3745723863], ["Bus", 0.227199264], ["Volkswagen", 0.220949264], ["Sightseeing", 0.220949264]]}, {"image": "//a.travel-assets.com/lxweb/media-vault/281293_l.jpeg?v=101827", "name": "Gourmet Food Tour of NoPa & Alamo Square", "moods": [{"mood": "adventurous", "score": 0.06595356213441483}, {"mood": "relaxed", "score": 0.033997621394943084}, {"mood": "romantic", "score": 0.01956843727090496}, {"mood": "comical", "score": 0.009672934290704833}], "latlng": [37.7763422, -122.4346334], "price": "$85", "type": "activity", "id": "281293", "keywords": [["Food", 0.6176952482], ["Tours", 0.4756451613], ["Bike", 0.277199264], ["Drink", 0.2718878636], ["Square", 0.2379814764]]}, {"image": "//a.travel-assets.com/lxweb/media-vault/179050_l.jpeg?v=101827", "name": "Santa Cruz Beach Train Adventure", "moods": [{"mood": "adventurous", "score": 0.19775104632550933}, {"mood": "romantic", "score": 0.07096093207569552}, {"mood": "comical", "score": 0.018928523616027898}, {"mood": "relaxed", "score": 0.0177968910744457}], "latlng": [37.0513374, -122.0732973], "price": "$29", "type": "activity", "id": "179050", "keywords": [["Day Trips", 0.2891945439], ["Trips", 0.2718878636], ["Excursions", 0.270949264], ["Adventure", 0.2700564069], ["Tours", 0.2378225806]]}, {"image": "//a.travel-assets.com/lxweb/media-vault/277323_l.jpeg?v=101827", "name": "Wine Country in the City Urban Tasting Tour", "moods": [{"mood": "adventurous", "score": 0.11540042029592124}, {"mood": "romantic", "score": 0.04304640720558078}, {"mood": "relaxed", "score": 0.041137686857381645}, {"mood": "comical", "score": 0.009672934290704833}], "latlng": [37.7749295, -122.4194155], "price": "$150", "type": "activity", "id": "277323", "keywords": [["Tours", 0.4887428044], ["Food", 0.33969668070000003], ["Bike", 0.277199264], ["Drink", 0.2718878636], ["Sightseeing", 0.270949264]]}, {"image": "//a.travel-assets.com/lxweb/media-vault/275405_l.jpeg?v=101827", "name": "Beers & Bikes Small-Group Tour", "moods": [{"mood": "adventurous", "score": 0.13222486929027982}, {"mood": "relaxed", "score": 0.04832076809534424}, {"mood": "romantic", "score": 0.04304640720558078}, {"mood": "comical", "score": 0.015856344781409664}], "latlng": [37.7749295, -122.4194155], "price": "$79", "type": "activity", "id": "275405", "keywords": [["Tours", 0.5756451613], ["Bike", 0.454398528], ["Food", 0.33969668070000003], ["Drink", 0.2718878636], ["Sightseeing", 0.270949264]]}, {"image": "//a.travel-assets.com/lxweb/media-vault/308266_l.jpeg?v=101827", "name": "Golden Gate Bridge Photo Tour", "moods": [{"mood": "adventurous", "score": 0.05644493718825268}, {"mood": "relaxed", "score": 0.011326270705637987}, {"mood": "comical", "score": 0.008585128656706116}], "latlng": [37.807485, -122.474904], "price": "$49", "type": "activity", "id": "308266", "keywords": [["Tours", 0.4756451613], ["Walking", 0.33969668070000003], ["Golden", 0.277199264], ["Bike Tours", 0.2588275715], ["Bike", 0.24602579460000001]]}, {"image": "//a.travel-assets.com/lxweb/media-vault/275353_l.jpeg?v=101827", "name": "Taste of the Wine Country Package", "moods": [{"mood": "adventurous", "score": 0.0660462023463582}, {"mood": "comical", "score": 0.024805160678277843}, {"mood": "romantic", "score": 0.020919849708345102}, {"mood": "relaxed", "score": 0.018199595848748716}], "latlng": [38.4274315, -122.3943299], "price": "$435", "type": "activity", "id": "275353", "keywords": [["Helicopter", 0.277199264], ["Balloon", 0.2718878636], ["Air", 0.26765873020000003], ["Package", 0.2613829375], ["Tours", 0.2378225806]]}, {"image": "//a.travel-assets.com/lxweb/media-vault/418942_l.jpeg?v=101827", "name": "Advanced Golden Gate Park Segway Tour", "moods": [{"mood": "adventurous", "score": 0.19170673163108873}, {"mood": "romantic", "score": 0.121005615494474}, {"mood": "comical", "score": 0.023809680046943702}, {"mood": "relaxed", "score": 0.018130580857020236}], "latlng": [37.76904, -122.4835193], "price": "$75", "type": "activity", "id": "418942", "keywords": [["Tours", 0.4887428044], ["Adventures", 0.33969668070000003], ["Sightseeing", 0.270949264], ["Gate", 0.227199264], ["Golden", 0.227199264]]}, {"image": "//a.travel-assets.com/lxweb/media-vault/386022_l.jpeg?v=101827", "name": "Grand City Yellow Bus Tour", "moods": [{"mood": "adventurous", "score": 0.11622630942167037}, {"mood": "romantic", "score": 0.03784818073762835}, {"mood": "relaxed", "score": 0.020758215689977308}], "latlng": [37.7749295, -122.4194155], "price": "$60", "type": "activity", "id": "386022", "keywords": [["Tours", 0.6815710872], ["Sightseeing", 0.270949264], ["Grand", 0.26852579460000003], ["City", 0.2447222222], ["Yellow", 0.227199264]]}, {"image": "//a.travel-assets.com/lxweb/media-vault/273063_l.jpeg?v=101827", "name": "Advanced Segway Tour of Hills, Lombard Street & the Waterfront", "moods": [{"mood": "adventurous", "score": 0.13839746996669722}, {"mood": "romantic", "score": 0.05678760536040952}, {"mood": "relaxed", "score": 0.046251227636931604}, {"mood": "comical", "score": 0.009672934290704833}], "latlng": [37.8079996, -122.4177434], "price": "$75", "type": "activity", "id": "273063", "keywords": [["Tours", 0.6815710872], ["Sightseeing", 0.3218878636], ["Bike", 0.277199264], ["Lombard", 0.220949264], ["Waterfront", 0.220949264]]}, {"image": "//a.travel-assets.com/lxweb/media-vault/307444_l.jpeg?v=101827", "name": "Lands End Walking Tour by Coastal Walkers", "moods": [{"mood": "adventurous", "score": 0.07333048920152191}, {"mood": "relaxed", "score": 0.018053866430408985}, {"mood": "comical", "score": 0.010999633400003612}, {"mood": "romantic", "score": 0.005857943403373729}], "latlng": [37.779696, -122.5109383], "price": "$49", "type": "activity", "id": "307444", "keywords": [["Walking", 0.6176952482], ["Tours", 0.4756451613], ["Bike", 0.2718878636], ["Walkers", 0.2700564069], ["Bike Tours", 0.2588275715]]}, {"image": "//a.travel-assets.com/lxweb/media-vault/281297_l.jpeg?v=101827", "name": "Gourmet Food Tour of Russian Hill", "moods": [{"mood": "adventurous", "score": 0.06595356213441483}, {"mood": "relaxed", "score": 0.033997621394943084}, {"mood": "romantic", "score": 0.013815766729553236}, {"mood": "comical", "score": 0.009672934290704833}], "latlng": [37.8010963, -122.4195558], "price": "$80", "type": "activity", "id": "281297", "keywords": [["Food", 0.6176952482], ["Tours", 0.4756451613], ["Bike", 0.277199264], ["Drink", 0.2718878636], ["Russian", 0.2628225806]]}, {"image": "//a.travel-assets.com/lxweb/media-vault/249512_l.jpeg?v=101827", "name": "Muir Woods Expedition", "moods": [{"mood": "adventurous", "score": 0.1659520332609017}, {"mood": "relaxed", "score": 0.013646115458587677}, {"mood": "comical", "score": 0.004087086878498208}, {"mood": "romantic", "score": 0.002457343956196797}], "latlng": [37.8953689, -122.5780709], "price": "$79", "type": "activity", "id": "249512", "keywords": [["Day Trips", 0.2891945439], ["Excursions", 0.270949264], ["Trips", 0.24602579460000001], ["Tours", 0.2378225806], ["Expedition", 0.227199264]]}, {"image": "//a.travel-assets.com/lxweb/media-vault/281265_l.jpeg?v=101827", "name": "Chinatown Culinary Walking Tour", "moods": [{"mood": "adventurous", "score": 0.06595356213441483}, {"mood": "relaxed", "score": 0.0300413723511156}, {"mood": "comical", "score": 0.009672934290704833}, {"mood": "romantic", "score": 0.00792134392094958}], "latlng": [37.7749295, -122.4194155], "price": "$69", "type": "activity", "id": "281265", "keywords": [["Tours", 0.4756451613], ["Walking", 0.4245515892], ["Food", 0.33969668070000003], ["Bike", 0.277199264], ["Drink", 0.2718878636]]}, {"image": "//a.travel-assets.com/lxweb/media-vault/310646_l.jpeg?v=101827", "name": "Ultimate Sky Tour by Fly Bay Area", "moods": [{"mood": "adventurous", "score": 0.0698818947364909}, {"mood": "comical", "score": 0.01710293738965008}, {"mood": "romantic", "score": 0.014601014999826224}, {"mood": "relaxed", "score": 0.0018131174981014058}], "latlng": [37.7749295, -122.4194155], "price": "$259", "type": "activity", "id": "310646", "keywords": [["Tours", 0.4756451613], ["Helicopter Tours", 0.2886352638], ["Balloon", 0.2718878636], ["Helicopter", 0.26602579460000003], ["Fly", 0.227199264]]}, {"image": "//a.travel-assets.com/lxweb/media-vault/277305_l.jpeg?v=101827", "name": "Mission Sweets Food Tour", "moods": [{"mood": "adventurous", "score": 0.10985108778496172}, {"mood": "romantic", "score": 0.04894083001418444}, {"mood": "relaxed", "score": 0.03470665293743733}], "latlng": [37.7598648, -122.4147977], "price": "$55", "type": "activity", "id": "277305", "keywords": [["Food", 0.6176952482], ["Tours", 0.5756451613], ["Drink", 0.2718878636], ["Sightseeing", 0.270949264], ["Walking", 0.26852579460000003]]}, {"image": "//a.travel-assets.com/lxweb/media-vault/226923_l.jpeg?v=101827", "name": "Magic Bus City Sightseeing Tour", "moods": [{"mood": "adventurous", "score": 0.20619427268719412}, {"mood": "romantic", "score": 0.11226469026838497}, {"mood": "relaxed", "score": 0.03771921875328173}], "latlng": [37.7749295, -122.4194155], "price": "$70", "type": "activity", "id": "226923", "keywords": [["Tours", 0.6815710872], ["Sightseeing", 0.616898528], ["Magic", 0.277199264], ["City", 0.2447222222], ["Bus", 0.227199264]]}, {"image": "//a.travel-assets.com/lxweb/media-vault/334738_l.jpeg?v=101827", "name": "Waterfront Segway Experience Tour", "moods": [{"mood": "adventurous", "score": 0.06037717389105185}, {"mood": "relaxed", "score": 0.031137748327991904}, {"mood": "romantic", "score": 0.015059012292503135}, {"mood": "comical", "score": 0.008585128656706116}], "latlng": [37.7749295, -122.4194155], "price": "$60", "type": "activity", "id": "334738", "keywords": [["Tours", 0.4756451613], ["Walking", 0.33969668070000003], ["Bike Tours", 0.2588275715], ["Bike", 0.24602579460000001], ["Waterfront", 0.220949264]]}, {"image": "//a.travel-assets.com/lxweb/media-vault/277319_l.jpeg?v=101827", "name": "North Beach Pub Crawl", "moods": [{"mood": "romantic", "score": 0.047713755646935176}, {"mood": "adventurous", "score": 0.04234505380300956}, {"mood": "relaxed", "score": 0.038237707564510136}, {"mood": "comical", "score": 0.001994508856720288}], "latlng": [37.8060532, -122.4103311], "price": "$60", "type": "activity", "id": "277319", "keywords": [["Food", 0.33969668070000003], ["Nightlife", 0.277199264], ["Drink", 0.2718878636], ["Walking", 0.26852579460000003], ["Tours", 0.2378225806]]}, {"image": "//a.travel-assets.com/lxweb/media-vault/310874_l.jpeg?v=101827", "name": "Dual U-Fly Adventure Tour", "moods": [{"mood": "adventurous", "score": 0.12392401569142703}, {"mood": "romantic", "score": 0.06326399296745026}, {"mood": "comical", "score": 0.02659279949056134}, {"mood": "relaxed", "score": 0.02071869368273184}], "latlng": [37.7749295, -122.4194155], "price": "$519", "type": "activity", "id": "310874", "keywords": [["Tours", 0.4756451613], ["Balloon", 0.2718878636], ["Air", 0.23856782110000002], ["Helicopter Tours", 0.2276757056], ["Adventure", 0.227199264]]}, {"image": "//a.travel-assets.com/lxweb/media-vault/277283_l.jpeg?v=101827", "name": "South Mission District Food Tour", "moods": [{"mood": "adventurous", "score": 0.10985108778496172}, {"mood": "romantic", "score": 0.04894083001418444}, {"mood": "relaxed", "score": 0.03470665293743733}], "latlng": [37.7749295, -122.4194155], "price": "$99", "type": "activity", "id": "277283", "keywords": [["Food", 0.6176952482], ["Tours", 0.5756451613], ["Drink", 0.2718878636], ["Sightseeing", 0.270949264], ["Walking", 0.26852579460000003]]}, {"image": "//a.travel-assets.com/lxweb/media-vault/277287_l.jpeg?v=101827", "name": "The Real Chinatown Food Tour", "moods": [{"mood": "adventurous", "score": 0.10985108778496172}, {"mood": "romantic", "score": 0.04894083001418444}, {"mood": "relaxed", "score": 0.03470665293743733}], "latlng": [37.7749295, -122.4194155], "price": "$99", "type": "activity", "id": "277287", "keywords": [["Food", 0.6176952482], ["Tours", 0.5756451613], ["Drink", 0.2718878636], ["Sightseeing", 0.270949264], ["Walking", 0.26852579460000003]]}, {"image": "//a.travel-assets.com/lxweb/media-vault/277279_l.jpeg?v=101827", "name": "Mission District Vegetarian Food Tour", "moods": [{"mood": "adventurous", "score": 0.10985108778496172}, {"mood": "romantic", "score": 0.04894083001418444}, {"mood": "relaxed", "score": 0.03470665293743733}], "latlng": [37.7598648, -122.4147977], "price": "$79", "type": "activity", "id": "277279", "keywords": [["Food", 0.6176952482], ["Tours", 0.5756451613], ["Drink", 0.2718878636], ["Sightseeing", 0.270949264], ["Walking", 0.26852579460000003]]}, {"image": "//a.travel-assets.com/lxweb/media-vault/219656_l.jpeg?v=101827", "name": "Bay Bridge Kayak Tour", "moods": [{"mood": "adventurous", "score": 0.1616001377103622}, {"mood": "romantic", "score": 0.04309190760513233}, {"mood": "comical", "score": 0.017462463786034475}, {"mood": "relaxed", "score": 0.014666826791614993}], "latlng": [37.7749295, -122.4194155], "price": "$82", "type": "activity", "id": "219656", "keywords": [["Tours", 0.6815710872], ["Sightseeing", 0.2960257946], ["Water", 0.27532258060000003], ["Kayak", 0.220949264], ["Bridge", 0.21852579460000002]]}, {"image": "//a.travel-assets.com/lxweb/media-vault/304248_l.jpeg?v=101827", "name": "Helicopter Flight with City Tour", "moods": [{"mood": "adventurous", "score": 0.12163728626671792}, {"mood": "comical", "score": 0.022732925274987225}, {"mood": "romantic", "score": 0.01288956926050166}, {"mood": "relaxed", "score": 0.0018131174981014058}], "latlng": [37.7749295, -122.4194155], "price": "$247", "type": "activity", "id": "304248", "keywords": [["Tours", 0.4756451613], ["Helicopter", 0.382853476], ["Helicopter Tours", 0.2886352638], ["Trips", 0.277199264], ["Balloon", 0.2718878636]]}, {"image": "//a.travel-assets.com/lxweb/media-vault/304242_l.jpeg?v=101827", "name": "Helicopter Tour with Muir Woods Visit", "moods": [{"mood": "adventurous", "score": 0.18672456656981842}, {"mood": "comical", "score": 0.025021975449987223}, {"mood": "relaxed", "score": 0.014933865407828975}, {"mood": "romantic", "score": 0.014153411460969868}], "latlng": [37.8953689, -122.5780709], "price": "$247", "type": "activity", "id": "304242", "keywords": [["Tours", 0.5756451613], ["Helicopter", 0.430353476], ["Trips", 0.277199264], ["Balloon", 0.2718878636], ["Excursions", 0.270949264]]}, {"image": "//a.travel-assets.com/lxweb/media-vault/278139_l.jpeg?v=101827", "name": "North Beach Food & Wine Tour", "moods": [{"mood": "adventurous", "score": 0.10985108778496172}, {"mood": "romantic", "score": 0.04894083001418444}, {"mood": "relaxed", "score": 0.03470665293743733}], "latlng": [37.8060532, -122.4103311], "price": "$110", "type": "activity", "id": "278139", "keywords": [["Food", 0.6176952482], ["Tours", 0.5756451613], ["Drink", 0.2718878636], ["Sightseeing", 0.270949264], ["Walking", 0.26852579460000003]]}, {"image": "//a.travel-assets.com/lxweb/media-vault/277233_l.jpeg?v=101827", "name": "North Beach Walking Tour", "moods": [{"mood": "adventurous", "score": 0.1369631517141357}, {"mood": "romantic", "score": 0.06873022997263808}, {"mood": "relaxed", "score": 0.05881286307789883}, {"mood": "comical", "score": 0.014901818340811489}], "latlng": [37.8060532, -122.4103311], "price": "$40", "type": "activity", "id": "277233", "keywords": [["Tours", 0.6815710872], ["Walking", 0.4245515892], ["Sightseeing", 0.2960257946], ["Bike", 0.277199264], ["Beach", 0.227199264]]}, {"image": "//a.travel-assets.com/lxweb/media-vault/277261_l.jpeg?v=101827", "name": "The Real Fisherman's Wharf Walking Tour", "moods": [{"mood": "adventurous", "score": 0.14378542926389806}, {"mood": "romantic", "score": 0.04172859306790638}, {"mood": "relaxed", "score": 0.026820941214577683}, {"mood": "comical", "score": 0.011260493948944267}], "latlng": [37.8079996, -122.4177434], "price": "$40", "type": "activity", "id": "277261", "keywords": [["Tours", 0.7815710872], ["Walking", 0.4245515892], ["Sightseeing", 0.3218878636], ["Bike", 0.277199264], ["Wharf", 0.220949264]]}, {"image": "//a.travel-assets.com/lxweb/media-vault/219660_l.jpeg?v=101827", "name": "City by the Bay Family Kayaking Tour", "moods": [{"mood": "adventurous", "score": 0.13461304282333253}, {"mood": "romantic", "score": 0.04172859306790638}, {"mood": "relaxed", "score": 0.023216133354175623}, {"mood": "comical", "score": 0.013729400181965052}], "latlng": [37.7749295, -122.4194155], "price": "$71", "type": "activity", "id": "219660", "keywords": [["Tours", 0.7815710872], ["Water", 0.3253225806], ["Sightseeing", 0.3218878636], ["City", 0.2447222222], ["Kayaking", 0.220949264]]}, {"image": "//a.travel-assets.com/lxweb/media-vault/274709_l.jpeg?v=101827", "name": "Small-Group Bridge to the Beach Tour", "moods": [{"mood": "adventurous", "score": 0.11526466797246682}, {"mood": "romantic", "score": 0.035125063284631206}, {"mood": "relaxed", "score": 0.023753865729643126}, {"mood": "comical", "score": 0.009487591709633538}], "latlng": [37.7749295, -122.4194155], "price": "$48", "type": "activity", "id": "274709", "keywords": [["Tours", 0.5756451613], ["Walking", 0.33969668070000003], ["Bike", 0.2718878636], ["Sightseeing", 0.270949264], ["Bike Tours", 0.2588275715]]}, {"image": "//a.travel-assets.com/lxweb/media-vault/274713_l.jpeg?v=101827", "name": "Small-Group North Beach Walking Pub Tour", "moods": [{"mood": "adventurous", "score": 0.06595356213441483}, {"mood": "relaxed", "score": 0.029627374241895314}, {"mood": "comical", "score": 0.009672934290704833}, {"mood": "romantic", "score": 0.007304527368029551}], "latlng": [37.8060532, -122.4103311], "price": "$43", "type": "activity", "id": "274713", "keywords": [["Tours", 0.4756451613], ["Walking", 0.4245515892], ["Food", 0.3106057716], ["Bike", 0.277199264], ["Drink", 0.2718878636]]}, {"image": "//a.travel-assets.com/lxweb/media-vault/286301_l.jpeg?v=101827", "name": "Hidden Wineries of Napa & Sonoma Valley Tasting Tour", "moods": [{"mood": "adventurous", "score": 0.15781520965638124}, {"mood": "relaxed", "score": 0.0293012683379225}, {"mood": "romantic", "score": 0.0034590159441532714}], "latlng": [38.4274315, -122.3943299], "price": "$149", "type": "activity", "id": "286301", "keywords": [["Tours", 0.4756451613], ["Excursions", 0.3097757946], ["Day Trips", 0.2891945439], ["Drink", 0.277199264], ["Trips", 0.2718878636]]}, {"image": "//a.travel-assets.com/lxweb/media-vault/290717_l.jpeg?v=101827", "name": "Small-Group City Tour", "moods": [{"mood": "adventurous", "score": 0.14230325703463062}, {"mood": "relaxed", "score": 0.021666413448294116}, {"mood": "romantic", "score": 0.002457343956196797}], "latlng": [37.7749295, -122.4194155], "price": "$59", "type": "activity", "id": "290717", "keywords": [["Tours", 0.4756451613], ["Day Trips", 0.2891945439], ["Excursions", 0.270949264], ["Trips", 0.24602579460000001], ["City", 0.2447222222]]}, {"image": "//a.travel-assets.com/lxweb/media-vault/274717_l.jpeg?v=101827", "name": "Small-Group Flavors & Murals of the Mission Tour", "moods": [{"mood": "adventurous", "score": 0.06595356213441483}, {"mood": "relaxed", "score": 0.0300413723511156}, {"mood": "comical", "score": 0.009672934290704833}, {"mood": "romantic", "score": 0.00792134392094958}], "latlng": [37.7598648, -122.4147977], "price": "$74", "type": "activity", "id": "274717", "keywords": [["Tours", 0.4756451613], ["Food", 0.33969668070000003], ["Bike", 0.277199264], ["Drink", 0.2718878636], ["Walking", 0.26602579460000003]]}, {"image": "//a.travel-assets.com/lxweb/media-vault/274721_l.jpeg?v=101827", "name": "Teas, Temples & Beatniks Small-Group Tour", "moods": [{"mood": "adventurous", "score": 0.06595356213441483}, {"mood": "relaxed", "score": 0.03077558740242477}, {"mood": "romantic", "score": 0.022397372290621262}, {"mood": "comical", "score": 0.009672934290704833}], "latlng": [37.7941378, -122.4077914], "price": "$37", "type": "activity", "id": "274721", "keywords": [["Tours", 0.4756451613], ["Food", 0.33969668070000003], ["Bike", 0.277199264], ["Drink", 0.2718878636], ["Teas", 0.227199264]]}, {"image": "//a.travel-assets.com/lxweb/media-vault/401290_l.jpeg?v=101827", "name": "Seaplane Flight Over the Bay & Alcatraz Island Tour via Ferry", "moods": [{"mood": "adventurous", "score": 0.16228401267025752}, {"mood": "romantic", "score": 0.04748609717938619}, {"mood": "relaxed", "score": 0.022724975817805033}, {"mood": "comical", "score": 0.017354152681849852}], "latlng": [37.8269775, -122.4229555], "price": "$222", "type": "activity", "id": "401290", "keywords": [["Tours", 0.6815710872], ["Sightseeing", 0.3218878636], ["Helicopter", 0.277199264], ["Ferry", 0.2700564069], ["Flight", 0.2378225806]]}, {"image": "//a.travel-assets.com/lxweb/media-vault/187933_l.jpeg?v=101827", "name": "Dining at Hard Rock Cafe with Priority Seating", "moods": [{"mood": "adventurous", "score": 0.04242590981093012}, {"mood": "relaxed", "score": 0.03848918818160266}, {"mood": "romantic", "score": 0.032813585625392716}], "latlng": [37.7749295, -122.4194155], "price": "$28", "type": "activity", "id": "187933", "keywords": [["Food", 0.33969668070000003], ["Seating", 0.2878225806], ["Dining", 0.277199264], ["Drink", 0.2718878636], ["Rock", 0.2378225806]]}, {"image": "//a.travel-assets.com/lxweb/media-vault/273645_l.jpeg?v=101827", "name": "Private Segway Tour of Waterfront & Hills", "moods": [{"mood": "adventurous", "score": 0.14529011938257136}, {"mood": "romantic", "score": 0.04722192957389594}, {"mood": "relaxed", "score": 0.023627979105234655}, {"mood": "comical", "score": 0.009672934290704833}], "latlng": [37.7749295, -122.4194155], "price": "$115", "type": "activity", "id": "273645", "keywords": [["Tours", 0.4887428044], ["Private", 0.3311815817], ["Bike", 0.277199264], ["Sightseeing", 0.270949264], ["Walking", 0.26852579460000003]]}, {"image": "//a.travel-assets.com/lxweb/media-vault/273663_l.jpeg?v=101827", "name": "Private Golden Gate Park Segway Tour", "moods": [{"mood": "adventurous", "score": 0.14529011938257136}, {"mood": "romantic", "score": 0.04722192957389594}, {"mood": "relaxed", "score": 0.023627979105234655}, {"mood": "comical", "score": 0.009672934290704833}], "latlng": [37.76904, -122.4835193], "price": "$115", "type": "activity", "id": "273663", "keywords": [["Tours", 0.4887428044], ["Private", 0.3311815817], ["Bike", 0.277199264], ["Sightseeing", 0.270949264], ["Walking", 0.2402351963]]}, {"image": "//a.travel-assets.com/lxweb/media-vault/273681_l.jpeg?v=101827", "name": "Private Segway Night Tour", "moods": [{"mood": "adventurous", "score": 0.14282820763257137}, {"mood": "romantic", "score": 0.04722192957389594}, {"mood": "relaxed", "score": 0.021694614105234655}, {"mood": "comical", "score": 0.007928172390704832}], "latlng": [37.7935881, -122.3957955], "price": "$115", "type": "activity", "id": "273681", "keywords": [["Tours", 0.4887428044], ["Private", 0.3311815817], ["Sightseeing", 0.270949264], ["Walking", 0.26852579460000003], ["Bike", 0.227199264]]}, {"image": "//a.travel-assets.com/lxweb/media-vault/277271_l.jpeg?v=101827", "name": "Mission North Food Tour", "moods": [{"mood": "adventurous", "score": 0.10985108778496172}, {"mood": "romantic", "score": 0.04894083001418444}, {"mood": "relaxed", "score": 0.03470665293743733}], "latlng": [37.7598648, -122.4147977], "price": "$79", "type": "activity", "id": "277271", "keywords": [["Food", 0.6176952482], ["Tours", 0.5756451613], ["Drink", 0.2718878636], ["Sightseeing", 0.270949264], ["Walking", 0.26852579460000003]]}, {"image": "//a.travel-assets.com/lxweb/media-vault/219908_l.jpeg?v=101827", "name": "The Tech Museum of Innovation in Silicon Valley", "moods": [{"mood": "adventurous", "score": 0.03138578483375792}, {"mood": "romantic", "score": 0.027834015089886355}, {"mood": "relaxed", "score": 0.02156964961480483}, {"mood": "comical", "score": 0.01704716148620755}], "latlng": [37.331629, -121.8901264], "price": "$24", "type": "activity", "id": "219908", "keywords": [["Museum", 0.277199264], ["Tech", 0.277199264], ["Innovation", 0.27532258060000003], ["Attractions", 0.24174057370000002], ["Valley", 0.227199264]]}, {"image": "//a.travel-assets.com/lxweb/media-vault/290729_l.jpeg?v=101827", "name": "Small-Group Wine Country Tour in Sonoma", "moods": [{"mood": "adventurous", "score": 0.1501933454358258}, {"mood": "relaxed", "score": 0.02747571332028395}, {"mood": "romantic", "score": 0.0034192859163035567}], "latlng": [38.291859, -122.4580356], "price": "$72", "type": "activity", "id": "290729", "keywords": [["Tours", 0.4756451613], ["Day Trips", 0.2891945439], ["Drink", 0.277199264], ["Trips", 0.2718878636], ["Excursions", 0.270949264]]}, {"image": "//a.travel-assets.com/lxweb/media-vault/278153_l.jpeg?v=101827", "name": "Urban Hike in the Haight-Ashbury", "moods": [{"mood": "adventurous", "score": 0.1148010406907275}, {"mood": "romantic", "score": 0.04304640720558078}, {"mood": "relaxed", "score": 0.04111317254127077}, {"mood": "comical", "score": 0.009672934290704833}], "latlng": [37.7692204, -122.4481393], "price": "$45", "type": "activity", "id": "278153", "keywords": [["Tours", 0.48231182800000005], ["Food", 0.33969668070000003], ["Bike", 0.277199264], ["Drink", 0.2718878636], ["Sightseeing", 0.270949264]]}, {"image": "//a.travel-assets.com/lxweb/media-vault/290723_l.jpeg?v=101827", "name": "Small-Group Muir Woods & Sausalito Tour", "moods": [{"mood": "adventurous", "score": 0.19029001097622003}, {"mood": "romantic", "score": 0.03781157682734046}, {"mood": "relaxed", "score": 0.025599061651190413}], "latlng": [37.8590937, -122.4852507], "price": "$59", "type": "activity", "id": "290723", "keywords": [["Tours", 0.4756451613], ["Day Trips", 0.2891945439], ["Trips", 0.2718878636], ["Excursions", 0.270949264], ["Sightseeing", 0.270949264]]}, {"image": "//a.travel-assets.com/lxweb/media-vault/277291_l.jpeg?v=101827", "name": "North Beach & Chinatown Food Tour", "moods": [{"mood": "adventurous", "score": 0.10985108778496172}, {"mood": "romantic", "score": 0.04894083001418444}, {"mood": "relaxed", "score": 0.03470665293743733}], "latlng": [37.8060532, -122.4103311], "price": "$105", "type": "activity", "id": "277291", "keywords": [["Food", 0.6176952482], ["Tours", 0.5756451613], ["Drink", 0.2718878636], ["Sightseeing", 0.270949264], ["Walking", 0.26852579460000003]]}, {"image": "//a.travel-assets.com/lxweb/media-vault/277309_l.jpeg?v=101827", "name": "Little Saigon & the Tendernob Food Tour", "moods": [{"mood": "adventurous", "score": 0.1148010406907275}, {"mood": "romantic", "score": 0.04894083001418444}, {"mood": "relaxed", "score": 0.04506942158509826}, {"mood": "comical", "score": 0.009672934290704833}], "latlng": [37.7842596, -122.4177607], "price": "$79", "type": "activity", "id": "277309", "keywords": [["Food", 0.6176952482], ["Tours", 0.48231182800000005], ["Bike", 0.277199264], ["Drink", 0.2718878636], ["Sightseeing", 0.270949264]]}, {"image": "//a.travel-assets.com/lxweb/media-vault/250012_l.jpeg?v=101827", "name": "Sonoma County Public Brewery Vibe Tour", "moods": [{"mood": "adventurous", "score": 0.10053089178496172}, {"mood": "romantic", "score": 0.04687261093879615}, {"mood": "relaxed", "score": 0.030369212693609843}], "latlng": [38.5779555, -122.9888319], "price": "$85", "type": "activity", "id": "250012", "keywords": [["Tours", 0.4756451613], ["Food", 0.33969668070000003], ["Drink", 0.2718878636], ["Sightseeing", 0.270949264], ["County", 0.227199264]]}, {"image": "//a.travel-assets.com/lxweb/media-vault/277315_l.jpeg?v=101827", "name": "Ferry Building & Farmer\u2019s Market Food Tour", "moods": [{"mood": "adventurous", "score": 0.10035897396119181}, {"mood": "romantic", "score": 0.04525213083400225}, {"mood": "relaxed", "score": 0.03158677266162238}], "latlng": [37.7957395, -122.3933182], "price": "$99", "type": "activity", "id": "277315", "keywords": [["Tours", 0.4756451613], ["Food", 0.4444560401], ["Sightseeing", 0.270949264], ["Walking", 0.26852579460000003], ["Drink", 0.26602579460000003]]}, {"image": "//a.travel-assets.com/lxweb/media-vault/407818_l.jpeg?v=101827", "name": "Celebrate the Haight Beer Tour", "moods": [{"mood": "adventurous", "score": 0.06595356213441483}, {"mood": "relaxed", "score": 0.0300413723511156}, {"mood": "comical", "score": 0.009672934290704833}, {"mood": "romantic", "score": 0.00792134392094958}], "latlng": [37.7749295, -122.4194155], "price": "$79", "type": "activity", "id": "407818", "keywords": [["Tours", 0.4756451613], ["Food", 0.33969668070000003], ["Bike", 0.277199264], ["Celebrate", 0.27532258060000003], ["Drink", 0.2718878636]]}, {"image": "//a.travel-assets.com/lxweb/media-vault/286321_l.jpeg?v=101827", "name": "Guided Hike in Sonoma County with Picnic Lunch", "moods": [{"mood": "adventurous", "score": 0.24367485533338873}, {"mood": "romantic", "score": 0.14279654615391732}, {"mood": "relaxed", "score": 0.04631984412484621}, {"mood": "comical", "score": 0.023809680046943702}], "latlng": [38.5779555, -122.9888319], "price": "$109", "type": "activity", "id": "286321", "keywords": [["Tours", 0.4756451613], ["Adventures", 0.33969668070000003], ["Excursions", 0.270949264], ["Sightseeing", 0.270949264], ["Lunch", 0.2700564069]]}, {"image": "//a.travel-assets.com/lxweb/media-vault/286325_l.jpeg?v=101827", "name": "Guided Hike in Napa County with Picnic Lunch", "moods": [{"mood": "adventurous", "score": 0.24367485533338873}, {"mood": "romantic", "score": 0.14279654615391732}, {"mood": "relaxed", "score": 0.04631984412484621}, {"mood": "comical", "score": 0.023809680046943702}], "latlng": [38.5024689, -122.2653887], "price": "$109", "type": "activity", "id": "286325", "keywords": [["Tours", 0.4756451613], ["Adventures", 0.33969668070000003], ["Excursions", 0.270949264], ["Sightseeing", 0.270949264], ["Lunch", 0.2700564069]]}, {"image": "//a.travel-assets.com/lxweb/media-vault/286305_l.jpeg?v=101827", "name": "Jenner Coastal Kayak Tour", "moods": [{"mood": "adventurous", "score": 0.12009434281608417}, {"mood": "romantic", "score": 0.0858805522098428}, {"mood": "comical", "score": 0.03556963396505558}, {"mood": "relaxed", "score": 0.00612770760151289}], "latlng": [38.4497134, -123.1151969], "price": "$155", "type": "activity", "id": "286305", "keywords": [["Adventures", 0.33969668070000003], ["Water", 0.278655914], ["Tour", 0.2378225806], ["Coastal", 0.227199264], ["Jenner", 0.220949264]]}, {"image": "//a.travel-assets.com/lxweb/media-vault/285679_l.jpeg?v=101827", "name": "Private Whale Watching in the Farallon Islands", "moods": [{"mood": "adventurous", "score": 0.16378495673114465}, {"mood": "romantic", "score": 0.05122706128301142}, {"mood": "comical", "score": 0.012212173451633324}, {"mood": "relaxed", "score": 0.005130673789861411}], "latlng": [37.6982872, -123.0071354], "price": "$1,000", "type": "activity", "id": "285679", "keywords": [["Private", 0.4831153012], ["Tours", 0.48231182800000005], ["Cruises", 0.33969668070000003], ["Water", 0.2893714022], ["Watching", 0.27532258060000003]]}, {"image": "//a.travel-assets.com/lxweb/media-vault/286309_l.jpeg?v=101827", "name": "Russian River Kayak Tour with Picnic Lunch", "moods": [{"mood": "adventurous", "score": 0.12009434281608417}, {"mood": "romantic", "score": 0.1073942285888179}, {"mood": "comical", "score": 0.036021853498577026}, {"mood": "relaxed", "score": 0.021627341222515903}], "latlng": [38.6104658, -122.8691609], "price": "$155", "type": "activity", "id": "286309", "keywords": [["Adventures", 0.33969668070000003], ["Water", 0.2893714022], ["Lunch", 0.2700564069], ["Russian", 0.2628225806], ["Tour", 0.2378225806]]}, {"image": "//a.travel-assets.com/lxweb/media-vault/286313_l.jpeg?v=101827", "name": "Green Valley Pedal 'n' Paddle with Winetastings", "moods": [{"mood": "adventurous", "score": 0.11157761467456523}, {"mood": "romantic", "score": 0.09164540934201618}, {"mood": "comical", "score": 0.045101893519613585}, {"mood": "relaxed", "score": 0.019808982439666348}], "latlng": [38.2529705, -122.1621917], "price": "$175", "type": "activity", "id": "286313", "keywords": [["Adventures", 0.33969668070000003], ["Bike", 0.277199264], ["Water", 0.27532258060000003], ["Food", 0.2718878636], ["Walking", 0.26852579460000003]]}, {"image": "//a.travel-assets.com/lxweb/media-vault/286317_l.jpeg?v=101827", "name": "Napa Valley Pedal 'n' Paddle with Winetastings", "moods": [{"mood": "adventurous", "score": 0.11157761467456523}, {"mood": "romantic", "score": 0.09164540934201618}, {"mood": "comical", "score": 0.045101893519613585}, {"mood": "relaxed", "score": 0.019808982439666348}], "latlng": [38.2975381, -122.286865], "price": "$175", "type": "activity", "id": "286317", "keywords": [["Adventures", 0.33969668070000003], ["Bike", 0.277199264], ["Water", 0.27532258060000003], ["Food", 0.2718878636], ["Walking", 0.26852579460000003]]}, {"image": "//a.travel-assets.com/lxweb/media-vault/289541_l.jpeg?v=101827", "name": "Private Bay Sailing Cruise with Winetasting", "moods": [{"mood": "adventurous", "score": 0.26184605231574537}, {"mood": "romantic", "score": 0.08116484437262718}, {"mood": "comical", "score": 0.012212173451633324}, {"mood": "relaxed", "score": 0.007849389261011705}], "latlng": [37.6909682, -122.3107517], "price": "$450", "type": "activity", "id": "289541", "keywords": [["Cruises", 0.6176952482], ["Tours", 0.4887428044], ["Private", 0.4831153012], ["Water", 0.2893714022], ["Trips", 0.277199264]]}, {"image": "//a.travel-assets.com/lxweb/media-vault/289537_l.jpeg?v=101827", "name": "Private Coastal Bay Sightseeing Tour", "moods": [{"mood": "adventurous", "score": 0.23203631719554427}, {"mood": "romantic", "score": 0.10486084425227382}, {"mood": "relaxed", "score": 0.023188689733322963}, {"mood": "comical", "score": 0.012212173451633324}], "latlng": [37.6909682, -122.3107517], "price": "$600", "type": "activity", "id": "289537", "keywords": [["Tours", 0.493372434], ["Sightseeing", 0.441898528], ["Private", 0.38311530120000004], ["Cruises", 0.33969668070000003], ["Water", 0.2893714022]]}, {"image": "//a.travel-assets.com/lxweb/media-vault/256768_l.jpeg?v=101827", "name": "Chocolate Tour of San Francisco", "moods": [{"mood": "adventurous", "score": 0.10985108778496172}, {"mood": "romantic", "score": 0.04304640720558078}, {"mood": "relaxed", "score": 0.03075040389360984}], "latlng": [37.7908101, -122.3985221], "price": "$25", "type": "activity", "id": "256768", "keywords": [["Tours", 0.5756451613], ["Food", 0.33969668070000003], ["Drink", 0.2718878636], ["Sightseeing", 0.270949264], ["Francisco", 0.2700564069]]}, {"image": "//a.travel-assets.com/lxweb/media-vault/278149_l.jpeg?v=101827", "name": "Guided Shopping Tour with Lunch in Pacific Heights", "moods": [{"mood": "adventurous", "score": 0.1374944651620132}, {"mood": "romantic", "score": 0.0462309075899799}, {"mood": "relaxed", "score": 0.035699645286388026}, {"mood": "comical", "score": 0.025784570551193847}], "latlng": [37.7925153, -122.4382307], "price": "$100", "type": "activity", "id": "278149", "keywords": [["Tours", 0.6815710872], ["Sightseeing", 0.3218878636], ["Bike", 0.277199264], ["Heights", 0.2700564069], ["Guided", 0.22820321400000002]]}, {"image": "//a.travel-assets.com/lxweb/media-vault/286333_l.jpeg?v=101827", "name": "Pints \u2018n\u2019 Pedals Beer Tasting Bike Tour", "moods": [{"mood": "adventurous", "score": 0.1640181770374004}, {"mood": "romantic", "score": 0.09164540934201618}, {"mood": "comical", "score": 0.039229834353353366}, {"mood": "relaxed", "score": 0.027990575788634956}], "latlng": [38.4021359, -122.8238806], "price": "$139", "type": "activity", "id": "286333", "keywords": [["Tours", 0.4756451613], ["Bike", 0.441898528], ["Bike Tour", 0.40868474460000004], ["Adventures", 0.33969668070000003], ["Food", 0.2718878636]]}, {"image": "//a.travel-assets.com/lxweb/media-vault/275445_l.jpeg?v=101827", "name": "Private Full-Day Sonoma Wine Country Trail Tour", "moods": [{"mood": "adventurous", "score": 0.16580574786395064}, {"mood": "relaxed", "score": 0.0286547675791725}, {"mood": "romantic", "score": 0.018682142692174688}], "latlng": [38.291859, -122.4580356], "price": "$1,100", "type": "activity", "id": "275445", "keywords": [["Private", 0.4831153012], ["Tours", 0.4756451613], ["Excursions", 0.2960257946], ["Day Trips", 0.2891945439], ["Drink", 0.277199264]]}, {"image": "//a.travel-assets.com/lxweb/media-vault/256780_l.jpeg?v=101827", "name": "Ghostly Walking Tour", "moods": [{"mood": "adventurous", "score": 0.05551795205033519}, {"mood": "relaxed", "score": 0.010598299598968606}, {"mood": "comical", "score": 0.007928172390704832}], "latlng": [37.796187, -122.407433], "price": "$18", "type": "activity", "id": "256780", "keywords": [["Walking", 0.6176952482], ["Tours", 0.4756451613], ["Bike", 0.227199264], ["Ghostly", 0.220949264], ["Bike Tours", 0.1776757056]]}, {"image": "//a.travel-assets.com/lxweb/media-vault/286281_l.jpeg?v=101827", "name": "Calistoga Sip 'n' Cycle Wine Country Bike Tour", "moods": [{"mood": "adventurous", "score": 0.12420087720915016}, {"mood": "relaxed", "score": 0.032818751418451926}, {"mood": "comical", "score": 0.015420154306409665}, {"mood": "romantic", "score": 0.00030291434444292144}], "latlng": [38.5787965, -122.5797054], "price": "$149", "type": "activity", "id": "286281", "keywords": [["Tours", 0.4756451613], ["Bike", 0.441898528], ["Bike Tour", 0.40868474460000004], ["Excursions", 0.2960257946], ["Day Trips", 0.2891945439]]}, {"image": "//a.travel-assets.com/lxweb/media-vault/286285_l.jpeg?v=101827", "name": "Carneros Sip 'n' Cycle Wine Country Bike Tour", "moods": [{"mood": "adventurous", "score": 0.12420087720915016}, {"mood": "relaxed", "score": 0.032818751418451926}, {"mood": "comical", "score": 0.015420154306409665}, {"mood": "romantic", "score": 0.00030291434444292144}], "latlng": [38.2975381, -122.286865], "price": "$149", "type": "activity", "id": "286285", "keywords": [["Tours", 0.4756451613], ["Bike", 0.441898528], ["Bike Tour", 0.40868474460000004], ["Excursions", 0.2960257946], ["Day Trips", 0.2891945439]]}, {"image": "//a.travel-assets.com/lxweb/media-vault/286289_l.jpeg?v=101827", "name": "Healdsburg Sip 'n' Cycle Wine Country Bike Tour", "moods": [{"mood": "adventurous", "score": 0.12420087720915016}, {"mood": "relaxed", "score": 0.032818751418451926}, {"mood": "comical", "score": 0.015420154306409665}, {"mood": "romantic", "score": 0.00030291434444292144}], "latlng": [38.6104658, -122.8691609], "price": "$149", "type": "activity", "id": "286289", "keywords": [["Tours", 0.4756451613], ["Bike", 0.441898528], ["Bike Tour", 0.40868474460000004], ["Excursions", 0.2960257946], ["Day Trips", 0.2891945439]]}, {"image": "//a.travel-assets.com/lxweb/media-vault/286297_l.jpeg?v=101827", "name": "Velo \u2018n\u2019 Vino Wine Country Bike Ride & Tasting Tour", "moods": [{"mood": "adventurous", "score": 0.14171555758088622}, {"mood": "relaxed", "score": 0.05034116817045925}, {"mood": "comical", "score": 0.018473487631409664}, {"mood": "romantic", "score": 0.0010621505999690623}], "latlng": [38.6104658, -122.8691609], "price": "$149", "type": "activity", "id": "286297", "keywords": [["Bike", 0.529398528], ["Tours", 0.4756451613], ["Excursions", 0.3218878636], ["Day Trips", 0.2891945439], ["Drink", 0.277199264]]}, {"image": "//a.travel-assets.com/lxweb/media-vault/286293_l.jpeg?v=101827", "name": "Healdsburg Farm Fresh Bike Tour", "moods": [{"mood": "adventurous", "score": 0.12751555673415016}, {"mood": "relaxed", "score": 0.033948593427201926}, {"mood": "comical", "score": 0.015856344781409664}, {"mood": "romantic", "score": 0.00031698430831792146}], "latlng": [38.6104658, -122.8691609], "price": "$149", "type": "activity", "id": "286293", "keywords": [["Tours", 0.4756451613], ["Bike", 0.454398528], ["Bike Tour", 0.40868474460000004], ["Excursions", 0.3097757946], ["Day Trips", 0.2891945439]]}, {"image": "//a.travel-assets.com/lxweb/media-vault/280401_l.jpeg?v=101827", "name": "Smartphone-Guided Urban Scavenger Hunt", "moods": [{"mood": "adventurous", "score": 0.20535553413374777}, {"mood": "romantic", "score": 0.121005615494474}, {"mood": "comical", "score": 0.033482614337648535}, {"mood": "relaxed", "score": 0.028849127957887438}], "latlng": [37.7749295, -122.4194155], "price": "$38", "type": "activity", "id": "280401", "keywords": [["Tours", 0.4887428044], ["Adventures", 0.33969668070000003], ["Bike", 0.277199264], ["Sightseeing", 0.270949264], ["Walking", 0.26852579460000003]]}]}